concurrent_progressbar/__init__.py
concurrent_progressbar/concurrent.py
concurrent_progressbar-1.1.4.dist-info/METADATA
concurrent_progressbar-1.1.4.dist-info/WHEEL
concurrent_progressbar-1.1.4.dist-info/licenses/LICENSE
concurrent_progressbar-1.1.4.dist-info/RECORD
