Metadata-Version: 2.3
Name: concurrent_progressbar
Version: 1.1.4
Summary: This package is used to track the processes executed in the program. It will show individual progress bar for each task alloted using this package. It runs each task in separate process.
Author-email: "M. Rayyan Akhtar" <akhtar.rayyan@live.com>
License-File: LICENSE
Classifier: License :: OSI Approved :: MIT License
Classifier: Operating System :: OS Independent
Classifier: Programming Language :: Python :: 3
Requires-Python: >=3.8
